_myipip.so
myipip_pkg-0.0.1.dist-info/DESCRIPTION.rst
myipip_pkg-0.0.1.dist-info/METADATA
myipip_pkg-0.0.1.dist-info/RECORD
myipip_pkg-0.0.1.dist-info/WHEEL
myipip_pkg-0.0.1.dist-info/metadata.json
myipip_pkg-0.0.1.dist-info/top_level.txt
